scrapy_pyppeteer/__init__.py
scrapy_pyppeteer/_monkeypatches.py
scrapy_pyppeteer/handler.py
scrapy_pyppeteer/page.py
scrapy_pyppeteer-0.0.15.dist-info/LICENSE
scrapy_pyppeteer-0.0.15.dist-info/METADATA
scrapy_pyppeteer-0.0.15.dist-info/WHEEL
scrapy_pyppeteer-0.0.15.dist-info/top_level.txt
scrapy_pyppeteer-0.0.15.dist-info/RECORD
