Metadata-Version: 2.1
Name: scrapy-pyppeteer
Version: 0.0.15
Summary: Pyppeteer integration for Scrapy
Home-page: https://github.com/elacuesta/scrapy-pyppeteer
Author: Eugenio Lacuesta
Author-email: eugenio.lacuesta@gmail.com
License: BSD
Platform: UNKNOWN
Classifier: Development Status :: 3 - Alpha
Classifier: License :: OSI Approved :: BSD License
Classifier: Programming Language :: Python
Classifier: Programming Language :: Python :: 3.6
Classifier: Programming Language :: Python :: 3.7
Classifier: Programming Language :: Python :: 3.8
Classifier: Framework :: Scrapy
Classifier: Intended Audience :: Developers
Classifier: Topic :: Internet :: WWW/HTTP
Classifier: Topic :: Software Development :: Libraries :: Application Frameworks
Classifier: Topic :: Software Development :: Libraries :: Python Modules
Requires-Dist: scrapy (!=2.4.0,>=2.0)
Requires-Dist: pyppeteer (>=0.0.23)
